pygraph/__init__.py
pygraph/algorithms/__init__.py
pygraph/algorithms/accessibility.py
pygraph/algorithms/critical.py
pygraph/algorithms/cycles.py
pygraph/algorithms/filters/__init__.py
pygraph/algorithms/filters/find.py
pygraph/algorithms/filters/null.py
pygraph/algorithms/filters/radius.py
pygraph/algorithms/generators.py
pygraph/algorithms/heuristics/__init__.py
pygraph/algorithms/heuristics/chow.py
pygraph/algorithms/heuristics/euclidean.py
pygraph/algorithms/minmax.py
pygraph/algorithms/pagerank.py
pygraph/algorithms/searching.py
pygraph/algorithms/sorting.py
pygraph/algorithms/traversal.py
pygraph/algorithms/utils.py
pygraph/classes/__init__.py
pygraph/classes/digraph.py
pygraph/classes/exceptions.py
pygraph/classes/graph.py
pygraph/classes/hypergraph.py
pygraph/classes/unionfind.py
pygraph/mixins/__init__.py
pygraph/mixins/basegraph.py
pygraph/mixins/common.py
pygraph/mixins/labeling.py
pygraph/readwrite/__init__.py
pygraph/readwrite/dot.py
pygraph/readwrite/markup.py
python_graph-2.0.0.dist-info/COPYING
python_graph-2.0.0.dist-info/METADATA
python_graph-2.0.0.dist-info/WHEEL
python_graph-2.0.0.dist-info/RECORD
