Metadata-Version: 2.3
Name: python-graph
Version: 2.0.0
Summary: A library for working with graphs in Python
License: MIT
Author: Pedro Matiello
Requires-Python: >=3.10
Classifier: License :: OSI Approved :: MIT License
Classifier: Programming Language :: Python :: 3
Classifier: Programming Language :: Python :: 3.10
Classifier: Programming Language :: Python :: 3.11
Classifier: Programming Language :: Python :: 3.12
Classifier: Programming Language :: Python :: 3.13
Provides-Extra: dot
Requires-Dist: pydot ; extra == "dot"
